omnicanvas/__init__.py
omnicanvas/canvas.py
omnicanvas/color.py
omnicanvas/colors.py
omnicanvas/exceptions.py
omnicanvas/graphics.py
omnicanvas/svg.py
omnicanvas-0.3.0.dist-info/DESCRIPTION.rst
omnicanvas-0.3.0.dist-info/METADATA
omnicanvas-0.3.0.dist-info/RECORD
omnicanvas-0.3.0.dist-info/WHEEL
omnicanvas-0.3.0.dist-info/metadata.json
omnicanvas-0.3.0.dist-info/top_level.txt
