Metadata-Version: 2.0
Name: omnicanvas
Version: 0.3.0
Summary: A Python generic canvas which can paint itself to SVG etc.
Home-page: https://omnicanvas.readthedocs.io
Author: Sam Ireland
Author-email: mail@samireland.com
License: MIT
Keywords: svg graphics canvas diagrams art
Platform: UNKNOWN
Classifier: Development Status :: 4 - Beta
Classifier: Intended Audience :: Other Audience
Classifier: License :: OSI Approved :: MIT License
Classifier: Topic :: Multimedia :: Graphics
Classifier: Programming Language :: Python :: 3
Classifier: Programming Language :: Python :: 3.0
Classifier: Programming Language :: Python :: 3.1
Classifier: Programming Language :: Python :: 3.2
Classifier: Programming Language :: Python :: 3.3
Classifier: Programming Language :: Python :: 3.4
Classifier: Programming Language :: Python :: 3.5
